AUTHORS
CHANGES
LICENSE
MANIFEST.in
README.rst
setup.py
Flask_Sentinel.egg-info/PKG-INFO
Flask_Sentinel.egg-info/SOURCES.txt
Flask_Sentinel.egg-info/dependency_links.txt
Flask_Sentinel.egg-info/requires.txt
Flask_Sentinel.egg-info/top_level.txt
flask_sentinel/__init__.py
flask_sentinel/basicauth.py
flask_sentinel/core.py
flask_sentinel/data.py
flask_sentinel/flask_sentinel.py
flask_sentinel/models.py
flask_sentinel/utils.py
flask_sentinel/validator.py
flask_sentinel/views.py
flask_sentinel/scripts/__init__.py
flask_sentinel/scripts/user.py
flask_sentinel/templates/management.html
flask_sentinel/tests/__init__.py
flask_sentinel/tests/base.py
flask_sentinel/tests/tests.py