Metadata-Version: 1.1
Name: Flask-Sentinel
Version: 0.0.4
Summary: OAuth2 Provider for Flask applications.
Home-page: https://github.com/nicolaiarocci/flask-sentinel
Author: Nicola Iarocci
Author-email: nicola@nicolaiarocci.com
License: BSD
Platform: any
Classifier: Development Status :: 3 - Alpha
Classifier: Environment :: Web Environment
Classifier: Intended Audience :: Developers
Classifier: License :: OSI Approved :: BSD License
Classifier: Operating System :: OS Independent
Classifier: Programming Language :: Python
Classifier: Programming Language :: Python :: 2
Classifier: Programming Language :: Python :: 2.7
Classifier: Programming Language :: Python :: 3
Classifier: Programming Language :: Python :: 3.3
Classifier: Programming Language :: Python :: 3.4
Classifier: Topic :: Internet :: WWW/HTTP :: Dynamic Content
